{
  "id": 6,
  "name": "Streets of Rage 2 Original Soundtrack",
  "description": "The \"Streets of Rage 2 Original Soundtrack\" is the music from the 1992 Sega Genesis/Mega Drive game, composed by Yuzo Koshiro with some contributions from Motohiro Kawashima according to Wikipedia. It's celebrated for its innovative blend of house, techno, and other electronic dance music styles, pushing the boundaries of what was possible on the 16-bit console's sound chip. The soundtrack is considered a classic and has been re-released in various formats, including vinyl and digital downloads",
  "image": "sor2.png",
  "price": 39.99
}
